{
  "theme_id": "standard",
  "name": "Corporate Navy Professional Theme",
  "description": "Professional navy blue theme with orange accents and DALL-E image generation",
  "version": "4.0.0",
  
  "colors": {
    "primary": "#0A2540",
    "primary_dark": "#051528",
    "primary_light": "#1E3A5F",
    
    "secondary": "#06B6D4",
    "secondary_dark": "#0891B2",
    "secondary_light": "#22D3EE",
    
    "accent": "#F97316",
    "accent_dark": "#EA580C",
    "accent_light": "#FB923C",
    
    "sidebar": "#1E293B",
    "sidebar_light": "#334155",
    
    "background": "#F8F9FA",
    "background_alt": "#FFFFFF",
    "background_card": "#FFFFFF",
    
    "text_primary": "#1F2937",
    "text_secondary": "#4B5563",
    "text_muted": "#9CA3AF",
    "text_inverse": "#FFFFFF",
    "text_light": "#D1D5DB",
    
    "border": "#E5E7EB",
    "border_light": "#F3F4F6",
    "border_dark": "#D1D5DB",
    
    "success": "#10B981",
    "warning": "#F59E0B",
    "error": "#EF4444",
    "info": "#3B82F6",
    
    "chart_colors": {
      "color_1": "#06B6D4",
      "color_2": "#F97316",
      "color_3": "#8B5CF6",
      "color_4": "#10B981",
      "color_5": "#EF4444",
      "color_6": "#F59E0B",
      "color_7": "#3B82F6"
    }
  },
  
  "gradients": {
    "title_gradient": {
      "start": "#0A2540",
      "end": "#051528",
      "angle": 135
    },
    "content_gradient": {
      "start": "#F8F9FA",
      "end": "#E5E7EB",
      "angle": 180
    },
    "section_gradient": {
      "start": "#0A2540",
      "end": "#1E3A5F",
      "angle": 135
    },
    "accent_gradient": {
      "start": "#F97316",
      "end": "#EA580C",
      "angle": 90
    }
  },
  
  "typography": {
    "font_families": {
      "primary": "Calibri",
      "heading": "Calibri",
      "body": "Calibri",
      "monospace": "Consolas"
    },
    "font_sizes": {
      "title": 44,
      "heading_1": 36,
      "heading_2": 28,
      "heading_3": 24,
      "body": 16,
      "body_small": 14,
      "caption": 12,
      "tiny": 11,
      "table_header": 13,
      "table_body": 11
    },
    "font_weights": {
      "light": 300,
      "regular": 400,
      "semibold": 600,
      "bold": 700
    },
    "line_heights": {
      "tight": 1.1,
      "normal": 1.15,
      "relaxed": 1.3,
      "loose": 1.5
    }
  },
  
  "spacing": {
    "slide_padding": {
      "top": 0.38,
      "right": 0.5,
      "bottom": 0.5,
      "left": 0.85
    },
    "content_margins": {
      "top": 1.35,
      "left": 0.85,
      "right": 0.6,
      "bottom": 0.5
    },
    "element_spacing": {
      "tight": 0.05,
      "normal": 0.1,
      "relaxed": 0.15,
      "loose": 0.25
    },
    "sidebar_width": 0.15
  },
  
  "icons": {
    "default_size": 36,
    "sizes": {
      "tiny": 20,
      "small": 28,
      "medium": 36,
      "large": 52,
      "xlarge": 70,
      "huge": 80
    },
    "default_color": "secondary",
    
    "keyword_to_icon_map": {
      "introduction": "rocket-launch",
      "overview": "eye",
      "executive": "briefcase",
      "summary": "file-text",
      "conclusion": "check-circle",
      "thank": "hand-waving",
      "strategy": "target",
      "plan": "map-trifold",
      "roadmap": "road-horizon",
      "vision": "telescope",
      "financial": "currency-dollar",
      "budget": "coin",
      "pricing": "tag",
      "investment": "trend-up",
      "technology": "gear",
      "system": "network",
      "ai": "brain",
      "team": "users-three",
      "timeline": "clock",
      "phase": "steps",
      "methodology": "flow-arrow",
      "security": "shield-check",
      "innovation": "lightbulb",
      "goal": "target",
      "objective": "target",
      "data": "chart-pie-slice",
      "analytics": "chart-line",
      "success": "check-fat",
      "approach": "flow-arrow",
      "technical": "gear",
      "company": "buildings",
      "about": "info",
      "contact": "envelope",
      "default": "circle"
    },
    
    "intelligent_mapping": {
      "strategy_keywords": ["strategy", "strategic", "plan", "planning", "roadmap"],
      "finance_keywords": ["financial", "budget", "cost", "pricing", "investment", "revenue"],
      "growth_keywords": ["growth", "scale", "expansion", "increase"],
      "technology_keywords": ["technology", "technical", "system", "software", "platform"],
      "people_keywords": ["team", "people", "staff", "resources", "hiring"],
      "timeline_keywords": ["timeline", "schedule", "phase", "milestone", "deadline"],
      "security_keywords": ["security", "risk", "compliance", "safety"],
      "innovation_keywords": ["innovation", "creative", "new", "modern"],
      "problem_keywords": ["problem", "challenge", "issue", "risk"],
      "solution_keywords": ["solution", "answer", "resolve", "fix"],
      "goal_keywords": ["goal", "objective", "target", "aim"],
      "data_keywords": ["data", "analytics", "metrics", "insights"]
    }
  },
  
  "bullet_styles": {
    "level_1": {
      "symbol": "●",
      "color": "primary",
      "size": 9,
      "space_after": 10
    },
    "level_2": {
      "symbol": "•",
      "color": "text_secondary",
      "size": 7,
      "indent": 2,
      "space_after": 6
    }
  },
  
  "chart_colors": [
    "#06B6D4",
    "#F97316",
    "#8B5CF6",
    "#10B981",
    "#EF4444",
    "#F59E0B",
    "#3B82F6"
  ],
  
  "table_styles": {
    "header": {
      "background_color": "#10B981",
      "text_color": "#FFFFFF",
      "font_size": 13,
      "font_bold": true
    },
    "body": {
      "font_size": 11,
      "text_color": "#1F2937",
      "alternate_row_color": "#F8F9FA"
    },
    "border": {
      "color": "#E5E7EB",
      "width": 1
    },
    "rounded_corners": true,
    "corner_radius": 8000
  },
  
  "image_config": {
    "enabled": true,
    "default_position": "right",
    "container_bg": "#FFFFFF",
    "container_border": "#E5E7EB",
    "accent_bar_color": "#F97316",
    "accent_bar_height": 0.15,
    "corner_radius": 0.1,
    "shadow_enabled": true,
    "caption_enabled": true
  },
  
  "content_limits": {
    "max_bullets_per_slide": 5,
    "max_title_chars": 60,
    "max_bullet_chars": 100,
    "max_sub_bullets": 3,
    "max_table_rows": 8,
    "max_table_cols": 6,
    "max_chart_points": 7
  },
  
  "pagination": {
    "auto_split": true,
    "overflow_detection": true,
    "continuation_indicator": "continued"
  }
}
